_jpyinterpreter/__init__.py
_jpyinterpreter/annotations.py
_jpyinterpreter/conversions.py
_jpyinterpreter/jvm_setup.py
_jpyinterpreter/translator.py
timefold/solver/__init__.py
timefold/solver/_future.py
timefold/solver/_jpype_type_conversions.py
timefold/solver/_problem_change.py
timefold/solver/_solution_manager.py
timefold/solver/_solver.py
timefold/solver/_solver_factory.py
timefold/solver/_solver_manager.py
timefold/solver/_timefold_java_interop.py
timefold/solver/py.typed
timefold/solver/config/__init__.py
timefold/solver/config/_config.py
timefold/solver/config/py.typed
timefold/solver/domain/__init__.py
timefold/solver/domain/_annotations.py
timefold/solver/domain/_types.py
timefold/solver/domain/_value_range.py
timefold/solver/domain/_variable_listener.py
timefold/solver/heuristic/__init__.py
timefold/solver/heuristic/_nearby_selection.py
timefold/solver/jars/HdrHistogram-2.2.2.jar
timefold/solver/jars/LatencyUtils-2.0.3.jar
timefold/solver/jars/__init__.py
timefold/solver/jars/angus-activation-2.0.2.jar
timefold/solver/jars/apiguardian-api-1.1.2.jar
timefold/solver/jars/asm-9.8.jar
timefold/solver/jars/asm-analysis-9.8.jar
timefold/solver/jars/asm-tree-9.8.jar
timefold/solver/jars/asm-util-9.8.jar
timefold/solver/jars/assertj-core-3.27.3.jar
timefold/solver/jars/byte-buddy-1.17.5.jar
timefold/solver/jars/byte-buddy-agent-1.17.5.jar
timefold/solver/jars/commons-collections4-4.5.0.jar
timefold/solver/jars/commons-math3-3.6.1.jar
timefold/solver/jars/gizmo-1.9.0.jar
timefold/solver/jars/istack-commons-runtime-4.1.2.jar
timefold/solver/jars/jakarta.activation-api-2.1.3.jar
timefold/solver/jars/jakarta.xml.bind-api-4.0.2.jar
timefold/solver/jars/jandex-3.3.1.jar
timefold/solver/jars/jaxb-core-4.0.5.jar
timefold/solver/jars/jaxb-runtime-4.0.5.jar
timefold/solver/jars/jpyinterpreter-1.24.0.jar
timefold/solver/jars/jspecify-1.0.0.jar
timefold/solver/jars/junit-jupiter-api-5.13.3.jar
timefold/solver/jars/junit-jupiter-engine-5.13.3.jar
timefold-1.24.0b0.dist-info/licenses/LICENSE.txt
timefold-1.24.0b0.dist-info/METADATA
timefold-1.24.0b0.dist-info/WHEEL
timefold-1.24.0b0.dist-info/top_level.txt
timefold-1.24.0b0.dist-info/RECORD
