Metadata-Version: 2.4
Name: timefold
Version: 1.24.0b0
Summary: An AI constraint solver that optimizes planning and scheduling problems
Home-page: https://github.com/TimefoldAI/timefold-solver
License: Apache License Version 2.0
Project-URL: Timefold Solver Documentation, https://timefold.ai/docs/timefold-solver/latest
Project-URL: Timefold Solver Homepage, https://solver.timefold.ai
Classifier: Development Status :: 4 - Beta
Classifier: Programming Language :: Python :: 3
Classifier: Topic :: Scientific/Engineering :: Artificial Intelligence
Classifier: Topic :: Software Development :: Libraries :: Java Libraries
Classifier: License :: OSI Approved :: Apache Software License
Classifier: Operating System :: OS Independent
Requires-Python: >=3.10
License-File: LICENSE.txt
Requires-Dist: JPype1==1.5.1
Dynamic: classifier
Dynamic: description
Dynamic: description-content-type
Dynamic: home-page
Dynamic: license
Dynamic: license-file
Dynamic: project-url
Dynamic: requires-dist
Dynamic: requires-python
Dynamic: summary
